swagger_client/__init__.py
swagger_client/api_client.py
swagger_client/configuration.py
swagger_client/rest.py
swagger_client/api/__init__.py
swagger_client/api/application_controller_api.py
swagger_client/api/intent_management_api.py
swagger_client/api/module_management_api.py
swagger_client/api/public_ap_is_api.py
swagger_client/api/tf_output_management_api.py
swagger_client/api/ui_accounts_controller_api.py
swagger_client/api/ui_application_controller_api.py
swagger_client/api/ui_artifact_ci_controller_api.py
swagger_client/api/ui_artifact_hub_controller_api.py
swagger_client/api/ui_artifact_routing_rule_controller_api.py
swagger_client/api/ui_artifactory_controller_api.py
swagger_client/api/ui_artifacts_controller_api.py
swagger_client/api/ui_assistant_controller_api.py
swagger_client/api/ui_audit_logs_controller_api.py
swagger_client/api/ui_aws_cluster_controller_api.py
swagger_client/api/ui_azure_cluster_controller_api.py
swagger_client/api/ui_billing_controller_api.py
swagger_client/api/ui_blueprint_designer_controller_api.py
swagger_client/api/ui_chat_gpt_controller_api.py
swagger_client/api/ui_ci_cd_controller_api.py
swagger_client/api/ui_cloud_cost_explorer_controller_api.py
swagger_client/api/ui_coder_controller_api.py
swagger_client/api/ui_common_cluster_controller_api.py
swagger_client/api/ui_custom_content_controller_api.py
swagger_client/api/ui_custom_role_controller_api.py
swagger_client/api/ui_delivery_pipeline_controller_api.py
swagger_client/api/ui_deployment_controller_api.py
swagger_client/api/ui_domain_mapping_controller_api.py
swagger_client/api/ui_dropdowns_controller_api.py
swagger_client/api/ui_environment_controller_api.py
swagger_client/api/ui_gcp_cluster_controller_api.py
swagger_client/api/ui_k_8s_cluster_controller_api.py
swagger_client/api/ui_kubernetes_explorer_controller_api.py
swagger_client/api/ui_maintenance_window_controller_api.py
swagger_client/api/ui_no_auth_user_controller_api.py
facets_control_plane_sdk-1.0.4.dist-info/METADATA
facets_control_plane_sdk-1.0.4.dist-info/WHEEL
facets_control_plane_sdk-1.0.4.dist-info/top_level.txt
facets_control_plane_sdk-1.0.4.dist-info/RECORD
