Metadata-Version: 2.1
Name: facets-control-plane-sdk
Version: 1.0.4
Summary: Api Documentation
Home-page: https://github.com/Facets-cloud/control-plane-python-sdk
Author: Anuj Hydrabadi
Author-email: anuj.hydrabadi@facets.cloud
Keywords: Swagger,Api Documentation
Classifier: Programming Language :: Python :: 3
Classifier: License :: OSI Approved :: MIT License
Classifier: Operating System :: OS Independent
Requires-Python: >=3.10
Requires-Dist: urllib3>=1.15
Requires-Dist: six>=1.10
Requires-Dist: certifi
Requires-Dist: python-dateutil
